MANIFEST.in
NEWS.txt
README.rst
setup.py
src/hive_utils/__init__.py
src/hive_utils/hive_client.py
src/hive_utils.egg-info/PKG-INFO
src/hive_utils.egg-info/SOURCES.txt
src/hive_utils.egg-info/dependency_links.txt
src/hive_utils.egg-info/requires.txt
src/hive_utils.egg-info/top_level.txt
src/hive_utils.egg-info/zip-safe