Metadata-Version: 1.0
Name: hive-utils
Version: 0.0.1
Summary: UNKNOWN
Home-page: https://github.com/eventbrite/python_hive_utils
Author: UNKNOWN
Author-email: UNKNOWN
License: BSD
Platform: UNKNOWN
Classifier: License :: OSI Approved :: BSD License
